liman/__init__.py
liman/agent.py
liman/conf.py
liman/loader.py
liman/py.typed
liman/state.py
liman/executor/__init__.py
liman/executor/base.py
liman/executor/schemas.py
liman-0.1.0a4.dist-info/METADATA
liman-0.1.0a4.dist-info/WHEEL
liman-0.1.0a4.dist-info/RECORD
