Metadata-Version: 2.4
Name: liman
Version: 0.1.0a4
Summary: Liman AgentOps
Author-email: Guro Bokum <jiojiajiu@gmail.com>
License-Expression: MIT
Classifier: License :: OSI Approved :: MIT License
Classifier: Operating System :: OS Independent
Classifier: Programming Language :: Python :: 3
Requires-Python: >=3.10
Requires-Dist: langchain-core>=0.3.67
Requires-Dist: liman-openapi
Requires-Dist: ruamel-yaml>=0.18.14
